virtual_landmark/__init__.py
virtual_landmark/abstract_landmark.py
virtual_landmark/calculus.py
virtual_landmark/decorator.py
virtual_landmark/virtual_landmark.py
virtual_landmark/virtual_pose_landmark.py
virtual_landmark/drawing_utils/__init__.py
virtual_landmark/drawing_utils/connections.py
virtual_landmark/drawing_utils/style.py
virtual_landmark-0.1.2.dist-info/licenses/LICENSE
virtual_landmark-0.1.2.dist-info/METADATA
virtual_landmark-0.1.2.dist-info/WHEEL
virtual_landmark-0.1.2.dist-info/top_level.txt
virtual_landmark-0.1.2.dist-info/RECORD
