Metadata-Version: 2.4
Name: virtual-landmark
Version: 0.1.2
Summary: A Python package for defining custom landmarks in Mediapipe making easy to calculate some new virtual points with a single extention class
Author-email: "Denys G. Santos" <gsdenys@gmail.com>
License-Expression: Apache-2.0
Project-URL: Homepage, https://cvpose.github.io/virtual_landmark_python
Project-URL: Documentation, https://cvpose.github.io/virtual_landmark_python
Project-URL: Issues, https://github.com/cvpose/virtual_landmark_python/issues
Project-URL: Source, https://github.com/cvpose/virtual_landmark_python
Keywords: mediapipe,custom landmarks,ladmarks,pose estimation,computer vision,biomechanics,motion tracking
Classifier: Development Status :: 4 - Beta
Classifier: Intended Audience :: Developers
Classifier: Intended Audience :: Science/Research
Classifier: Topic :: Scientific/Engineering :: Image Recognition
Classifier: Topic :: Software Development :: Libraries :: Python Modules
Classifier: Programming Language :: Python :: 3
Classifier: Programming Language :: Python :: 3.10
Classifier: Programming Language :: Python :: 3.11
Classifier: Operating System :: OS Independent
Requires-Python: >=3.10
License-File: LICENSE
Requires-Dist: mediapipe>=0.10.0
Requires-Dist: numpy>=2.0.0
Requires-Dist: opencv-python>=4.7.0.72
Provides-Extra: dev
Requires-Dist: pytest; extra == "dev"
Requires-Dist: black; extra == "dev"
Requires-Dist: ruff; extra == "dev"
Requires-Dist: mypy; extra == "dev"
Dynamic: license-file
